[
  {
    "name": "Blue Rhino Propane Exchange",
    "address": "123 Main St",
    "city": "Houston",
    "state": "TX",
    "phone": "(713) 555-0100",
    "type": "exchange",
    "rating": 4.2,
    "website": ""
  },
  {
    "name": "Suburban Propane",
    "address": "456 Oak Ave",
    "city": "Houston",
    "state": "TX",
    "phone": "(713) 555-0200",
    "type": "refill,exchange",
    "rating": 4.5,
    "website": ""
  },
  {
    "name": "AmeriGas Propane",
    "address": "789 Pine Rd",
    "city": "Houston",
    "state": "TX",
    "phone": "(713) 555-0300",
    "type": "refill,exchange",
    "rating": 4.1,
    "website": ""
  },
  {
    "name": "Texas Propane Service",
    "address": "321 Cedar Ln",
    "city": "Dallas",
    "state": "TX",
    "phone": "(214) 555-0100",
    "type": "refill",
    "rating": 4.7,
    "website": ""
  },
  {
    "name": "Dallas Propane Depot",
    "address": "654 Elm St",
    "city": "Dallas",
    "state": "TX",
    "phone": "(214) 555-0200",
    "type": "exchange",
    "rating": 4.3,
    "website": ""
  },
  {
    "name": "Alamo Propane Co",
    "address": "987 Commerce St",
    "city": "San Antonio",
    "state": "TX",
    "phone": "(210) 555-0100",
    "type": "refill,exchange",
    "rating": 4.6,
    "website": ""
  },
  {
    "name": "San Antonio Propane Exchange",
    "address": "147 Houston Hwy",
    "city": "San Antonio",
    "state": "TX",
    "phone": "(210) 555-0200",
    "type": "exchange",
    "rating": 4.0,
    "website": ""
  },
  {
    "name": "Austin Propane & Gas",
    "address": "567 Congress Ave",
    "city": "Austin",
    "state": "TX",
    "phone": "(512) 555-0100",
    "type": "refill,exchange",
    "rating": 4.8,
    "website": ""
  },
  {
    "name": "Hill Country Propane",
    "address": "890 Lamar Blvd",
    "city": "Austin",
    "state": "TX",
    "phone": "(512) 555-0200",
    "type": "refill",
    "rating": 4.4,
    "website": ""
  }
]
